cordon/__init__.py
cordon/cli.py
cordon/pipeline.py
cordon/py.typed
cordon/analysis/__init__.py
cordon/analysis/scorer.py
cordon/analysis/thresholder.py
cordon/core/__init__.py
cordon/core/config.py
cordon/core/types.py
cordon/embedding/__init__.py
cordon/embedding/llama_cpp.py
cordon/embedding/remote.py
cordon/embedding/transformer.py
cordon/ingestion/__init__.py
cordon/ingestion/reader.py
cordon/postprocess/__init__.py
cordon/postprocess/formatter.py
cordon/postprocess/merger.py
cordon/segmentation/__init__.py
cordon/segmentation/windower.py
cordon-0.3.3.dist-info/METADATA
cordon-0.3.3.dist-info/WHEEL
cordon-0.3.3.dist-info/entry_points.txt
cordon-0.3.3.dist-info/licenses/LICENSE
cordon-0.3.3.dist-info/RECORD
