Metadata-Version: 2.4
Name: cordon
Version: 0.3.3
Summary: Semantic anomaly detection for system log files
Author-email: Caleb Evans <caevans@redhat.com>
License: Apache-2.0
License-File: LICENSE
Requires-Python: >=3.10
Requires-Dist: huggingface-hub>=0.20.0
Requires-Dist: litellm>=1.80.0
Requires-Dist: numpy>=1.24.0
Requires-Dist: sentence-transformers>=2.2.0
Requires-Dist: tokenizers>=0.20.0
Requires-Dist: torch>=2.0.0
Requires-Dist: tqdm>=4.65.0
Provides-Extra: benchmark
Requires-Dist: matplotlib>=3.7.0; extra == 'benchmark'
Requires-Dist: pyyaml>=6.0; extra == 'benchmark'
Requires-Dist: requests>=2.31.0; extra == 'benchmark'
Requires-Dist: scipy>=1.10.0; extra == 'benchmark'
Requires-Dist: seaborn>=0.12.0; extra == 'benchmark'
Requires-Dist: umap-learn>=0.5.0; extra == 'benchmark'
Provides-Extra: dev
Requires-Dist: mypy>=1.5.0; extra == 'dev'
Requires-Dist: pre-commit>=3.5.0; extra == 'dev'
Requires-Dist: pytest-cov>=4.1.0; extra == 'dev'
Requires-Dist: pytest>=7.4.0; extra == 'dev'
Requires-Dist: ruff>=0.1.0; extra == 'dev'
Provides-Extra: llama-cpp
Requires-Dist: huggingface-hub>=0.20.0; extra == 'llama-cpp'
Requires-Dist: llama-cpp-python>=0.3.0; extra == 'llama-cpp'
